Metadata-Version: 2.1
Name: cloudtoken-plugin.saml
Version: 0.1.764
Summary: SAML plugin for cloudtoken.
Home-page: https://bitbucket.org/atlassian/cloudtoken
Author: Atlassian Cloud Engineering
Author-email: cloud-team@atlassian.com
License: Apache
Platform: UNKNOWN
Requires-Python: >=3.5
Requires-Dist: boto3 (>=1.4.0)
Requires-Dist: cloudtoken (>=0.1.12)
